isbinary/__init__.py
isbinary/__main__.py
isbinary/_chardet.py
isbinary/check.py
isbinary/cli.py
isbinary/py.typed
isbinary-1.0.1.dist-info/LICENSE.txt
isbinary-1.0.1.dist-info/WHEEL
isbinary-1.0.1.dist-info/METADATA
isbinary-1.0.1.dist-info/RECORD
