Metadata-Version: 2.1
Name: isbinary
Version: 1.0.1
Summary: Lightweight pure Python package to check if a file is binary or text.
Home-page: https://github.com/djmattyg007/python-isbinary
License: BSD
Keywords: binary,file
Author: Matthew Gamble
Author-email: git@matthewgamble.net
Requires-Python: >=3.8,<4.0
Classifier: License :: Other/Proprietary License
Classifier: Programming Language :: Python :: 3
Classifier: Programming Language :: Python :: 3.10
Classifier: Programming Language :: Python :: 3.8
Classifier: Programming Language :: Python :: 3.9
Requires-Dist: chardet (>=3.0.2,<5.0.0)
Project-URL: Documentation, https://isbinary.readthedocs.io/
Project-URL: Repository, https://github.com/djmattyg007/python-isbinary
